qadf/__init__.py
qadf/bootstrap.py
qadf/core.py
qadf/critical_values.py
qadf/visualization.py
qadf-1.0.0.dist-info/licenses/LICENSE
qadf-1.0.0.dist-info/METADATA
qadf-1.0.0.dist-info/WHEEL
qadf-1.0.0.dist-info/top_level.txt
qadf-1.0.0.dist-info/RECORD
