Metadata-Version: 2.4
Name: qadf
Version: 1.0.0
Summary: Quantile ADF Unit Root Test - Implementation of Koenker & Xiao (2004)
Author-email: Dr Merwan Roudane <merwanroudane920@gmail.com>
Maintainer-email: Dr Merwan Roudane <merwanroudane920@gmail.com>
License: MIT
Project-URL: Homepage, https://github.com/merwanroudane/quantileadf
Project-URL: Documentation, https://github.com/merwanroudane/quantileadf#readme
Project-URL: Repository, https://github.com/merwanroudane/quantileadf
Project-URL: Issues, https://github.com/merwanroudane/quantileadf/issues
Project-URL: Changelog, https://github.com/merwanroudane/quantileadf/blob/main/CHANGELOG.md
Keywords: econometrics,unit root test,quantile regression,time series,cointegration,stationarity,ADF test,Koenker Xiao,QADF
Classifier: Development Status :: 5 - Production/Stable
Classifier: Intended Audience :: Science/Research
Classifier: Intended Audience :: Developers
Classifier: Intended Audience :: Education
Classifier: License :: OSI Approved :: MIT License
Classifier: Operating System :: OS Independent
Classifier: Programming Language :: Python :: 3
Classifier: Programming Language :: Python :: 3.8
Classifier: Programming Language :: Python :: 3.9
Classifier: Programming Language :: Python :: 3.10
Classifier: Programming Language :: Python :: 3.11
Classifier: Programming Language :: Python :: 3.12
Classifier: Topic :: Scientific/Engineering
Classifier: Topic :: Scientific/Engineering :: Mathematics
Classifier: Topic :: Scientific/Engineering :: Information Analysis
Requires-Python: >=3.8
License-File: LICENSE
Requires-Dist: numpy>=1.20.0
Requires-Dist: scipy>=1.7.0
Requires-Dist: pandas>=1.3.0
Requires-Dist: statsmodels>=0.13.0
Provides-Extra: dev
Requires-Dist: pytest>=7.0; extra == "dev"
Requires-Dist: pytest-cov>=4.0; extra == "dev"
Requires-Dist: black>=23.0; extra == "dev"
Requires-Dist: isort>=5.12; extra == "dev"
Requires-Dist: flake8>=6.0; extra == "dev"
Requires-Dist: mypy>=1.0; extra == "dev"
Provides-Extra: plotting
Requires-Dist: matplotlib>=3.5.0; extra == "plotting"
Provides-Extra: all
Requires-Dist: matplotlib>=3.5.0; extra == "all"
Requires-Dist: pytest>=7.0; extra == "all"
Requires-Dist: pytest-cov>=4.0; extra == "all"
Dynamic: license-file
